client/__init__.py
client/add_contact.py
client/client.py
client/database.py
client/del_contact.py
client/main_window.py
client/main_window_conv.py
client/start_dialog.py
client/transport.py
client_chat_pyqt_motr-0.1.dist-info/METADATA
client_chat_pyqt_motr-0.1.dist-info/WHEEL
client_chat_pyqt_motr-0.1.dist-info/top_level.txt
client_chat_pyqt_motr-0.1.dist-info/RECORD
