Metadata-Version: 2.1
Name: client_chat_pyqt_motr
Version: 0.1
Summary: Client packet
Author: Roman Motrich
Author-email: test@mail.ru
License: UNKNOWN
Platform: UNKNOWN
